pdm_audit-0.6.3.dist-info/METADATA
pdm_audit-0.6.3.dist-info/WHEEL
pdm_audit-0.6.3.dist-info/entry_points.txt
pdm_audit-0.6.3.dist-info/licenses/LICENSE
pdm_audit/__init__.py
pdm_audit/cli.py
pdm_audit/config.py
pdm_audit/executor.py
pdm_audit/plugin.py
pdm_audit/signal.py
pdm_audit/updates.py
pdm_audit-0.6.3.dist-info/RECORD
